DESCRIPTION.rst
MANIFEST.in
setup.cfg
setup.py
iodine/__init__.py
iodine/__main__.py
iodine/magic.py
iodine/magic_test.py
iodine/salt_rest.py
iodine/update.py
iodine.egg-info/PKG-INFO
iodine.egg-info/SOURCES.txt
iodine.egg-info/dependency_links.txt
iodine.egg-info/entry_points.txt
iodine.egg-info/pbr.json
iodine.egg-info/requires.txt
iodine.egg-info/top_level.txt