Metadata-Version: 1.1
Name: iodine
Version: 0.0.4
Summary: A salt-api client based on IPython
Home-page: https://bitbucket.org/jagguli/iodine
Author: Steven Joseph
Author-email: steven@stevenjoseph.in
License: MIT
Keywords: salt saltstack client ipython
Platform: UNKNOWN
Classifier: Development Status :: 3 - Alpha
Classifier: Intended Audience :: Developers
Classifier: Topic :: Software Development :: Build Tools
Classifier: License :: OSI Approved :: MIT License
Classifier: Programming Language :: Python :: 2
Classifier: Programming Language :: Python :: 2.6
Classifier: Programming Language :: Python :: 2.7
Classifier: Programming Language :: Python :: 3
Classifier: Programming Language :: Python :: 3.2
Classifier: Programming Language :: Python :: 3.3
Classifier: Programming Language :: Python :: 3.4
